pybpod_gui_plugin_emulator/__init__.py
pybpod_gui_plugin_emulator/emulator_gui.py
pybpod_gui_plugin_emulator/settings.py
pybpod_gui_plugin_emulator/models/__init__.py
pybpod_gui_plugin_emulator/models/setup/__init__.py
pybpod_gui_plugin_emulator/models/setup/setup_uibusy_emulator.py
pybpod_gui_plugin_emulator/models/setup/setup_window_emulator.py
pybpod_gui_plugin_emulator/resources/__init__.py
pybpod_gui_plugin_emulator/resources/checkbox_checked.svg
pybpod_gui_plugin_emulator/resources/checkbox_unchecked.svg
pybpod_gui_plugin_emulator/resources/develop_board.svg
pybpod_gui_plugin_emulator/resources/launch.svg
pybpod_gui_plugin_emulator-0.1.5.dist-info/AUTHORS.rst
pybpod_gui_plugin_emulator-0.1.5.dist-info/LICENSE
pybpod_gui_plugin_emulator-0.1.5.dist-info/METADATA
pybpod_gui_plugin_emulator-0.1.5.dist-info/WHEEL
pybpod_gui_plugin_emulator-0.1.5.dist-info/top_level.txt
pybpod_gui_plugin_emulator-0.1.5.dist-info/RECORD
