Metadata-Version: 2.1
Name: pybpod-gui-plugin-emulator
Version: 0.1.5
Summary: Emulator for PyBpod to work with the Bpod's State Machine ports.
Home-page: https://github.com/pybpod/pybpod-gui-plugin-emulator
Author: Luís Teixeira
Author-email: micboucinha@gmail.com
License: MIT
Project-URL: Documentation, https://pybpod-gui-plugin-emulator.readthedocs.io/
Project-URL: Changelog, https://pybpod-gui-plugin-emulator.readthedocs.io/en/latest/changelog.html
Project-URL: Issue Tracker, https://github.com/pybpod/pybpod-gui-plugin-emulator/issues
Platform: UNKNOWN
Classifier: Development Status :: 5 - Production/Stable
Classifier: Intended Audience :: Developers
Classifier: License :: OSI Approved :: MIT License
Classifier: Operating System :: Unix
Classifier: Operating System :: POSIX
Classifier: Operating System :: Microsoft :: Windows
Classifier: Programming Language :: Python :: 3.6
Classifier: Topic :: Utilities
Requires-Python: >=2.7, !=3.0.*, !=3.1.*, !=3.2.*, !=3.3.*
Requires-Dist: pybpod-api
